pxe.py
pxe-0.1.0.dist-info/LICENSE
pxe-0.1.0.dist-info/METADATA
pxe-0.1.0.dist-info/WHEEL
pxe-0.1.0.dist-info/entry_points.txt
pxe-0.1.0.dist-info/top_level.txt
pxe-0.1.0.dist-info/RECORD
